admcycles/DR.py
admcycles/GRRcomp.py
admcycles/__init__.py
admcycles/admcycles.py
admcycles/deprecations.py
admcycles/double_ramification_cycle.py
admcycles/graph_sum.py
admcycles/moduli.py
admcycles/stable_graph.py
admcycles/stratarecursion.py
admcycles/superseded.py
admcycles/tautological_ring.py
admcycles/diffstrata/__init__.py
admcycles/diffstrata/additivegenerator.py
admcycles/diffstrata/adm_eval_cache.py
admcycles/diffstrata/auxiliary.py
admcycles/diffstrata/bic.py
admcycles/diffstrata/cache.py
admcycles/diffstrata/elgtautclass.py
admcycles/diffstrata/embeddedlevelgraph.py
admcycles/diffstrata/generalisedstratum.py
admcycles/diffstrata/klevelgraph.py
admcycles/diffstrata/levelgraph.py
admcycles/diffstrata/sig.py
admcycles/diffstrata/stratatautring.py
admcycles/diffstrata/tests.py
admcycles/diffstrata/xi_cache.py
admcycles-1.3.2.dist-info/DESCRIPTION.rst
admcycles-1.3.2.dist-info/METADATA
admcycles-1.3.2.dist-info/RECORD
admcycles-1.3.2.dist-info/WHEEL
admcycles-1.3.2.dist-info/metadata.json
admcycles-1.3.2.dist-info/top_level.txt
