Metadata-Version: 2.0
Name: admcycles
Version: 1.3.2
Summary: Tautological ring on Mbar_g,n
Home-page: https://gitlab.com/jo314schmitt/admcycles
Author: Vincent Delecroix, Aaron Pixton, Johannes Schmitt, Jason van Zelm, Jonathan Zachhuber
Author-email: jo314schmitt@gmail.com
License: GPLv2+
Keywords: SageMath geometry moduli space curve
Platform: UNKNOWN
Classifier: Development Status :: 5 - Production/Stable
Classifier: Intended Audience :: Science/Research
Classifier: Topic :: Scientific/Engineering :: Mathematics
Classifier: License :: OSI Approved :: GNU General Public License v2 or later (GPLv2+)
Classifier: Programming Language :: Python :: 2.7
Classifier: Programming Language :: Python :: 3
